autokattis/__init__.py
autokattis/api/__init__.py
autokattis/api/databasemanager.py
autokattis/api/enums.py
autokattis/api/loginmanager.py
autokattis/api/nuskattis.py
autokattis/api/openkattis.py
autokattis/api/utils.py
autokattis-2.1.3.dist-info/LICENSE
autokattis-2.1.3.dist-info/METADATA
autokattis-2.1.3.dist-info/WHEEL
autokattis-2.1.3.dist-info/top_level.txt
autokattis-2.1.3.dist-info/RECORD
