Metadata-Version: 2.1
Name: autokattis
Version: 2.1.3
Summary: Updated Kattis API wrapper
Home-page: https://github.com/RussellDash332/autokattis
Download-URL: https://pypi.org/project/autokattis/
Author: Russell Saerang
Author-email: russellsaerang@gmail.com
License: MIT
Keywords: Kattis
License-File: LICENSE
Requires-Dist: requests
Requires-Dist: beautifulsoup4
Requires-Dist: lxml
Requires-Dist: pandas
Requires-Dist: matplotlib
Requires-Dist: seaborn
Requires-Dist: thefuzz
Requires-Dist: thefuzz[speedup]
